windsurf_mcp_config_manager/__init__.py
windsurf_mcp_config_manager/cli.py
windsurf_mcp_config_manager-0.2.1.dist-info/licenses/LICENSE
windsurf_mcp_config_manager-0.2.1.dist-info/METADATA
windsurf_mcp_config_manager-0.2.1.dist-info/WHEEL
windsurf_mcp_config_manager-0.2.1.dist-info/entry_points.txt
windsurf_mcp_config_manager-0.2.1.dist-info/top_level.txt
windsurf_mcp_config_manager-0.2.1.dist-info/RECORD
