Metadata-Version: 2.4
Name: windsurf-mcp-config-manager
Version: 0.2.1
Summary: A utility to manage Windsurf MCP server configurations
Home-page: https://github.com/trilogy-group/trilogy-group-windsurf-mcp-config-manager
Author: Windsurf Team
Author-email: your.email@example.com
Classifier: Programming Language :: Python :: 3
Classifier: License :: OSI Approved :: MIT License
Classifier: Operating System :: OS Independent
Requires-Python: >=3.6
License-File: LICENSE
Requires-Dist: click
Requires-Dist: requests
Requires-Dist: tabulate
Dynamic: author
Dynamic: author-email
Dynamic: classifier
Dynamic: description
Dynamic: description-content-type
Dynamic: home-page
Dynamic: license-file
Dynamic: requires-dist
Dynamic: requires-python
Dynamic: summary
